jsonclasses/__init__.py
jsonclasses/cdef.py
jsonclasses/cgraph.py
jsonclasses/config.py
jsonclasses/ctx.py
jsonclasses/ctxs.py
jsonclasses/encoder.py
jsonclasses/exceptions.py
jsonclasses/excs.py
jsonclasses/fdef.py
jsonclasses/isjsonclass.py
jsonclasses/jconf.py
jsonclasses/jfield.py
jsonclasses/jobject.py
jsonclasses/json_encoder.py
jsonclasses/jsonclass.py
jsonclasses/jsonclassify.py
jsonclasses/jsondict.py
jsonclasses/jsonenum.py
jsonclasses/keypath.py
jsonclasses/mark_graph.py
jsonclasses/mgraph.py
jsonclasses/mypy.py
jsonclasses/object_dict.py
jsonclasses/objref.py
jsonclasses/odict.py
jsonclasses/ograph.py
jsonclasses/olist.py
jsonclasses/orm.py
jsonclasses/orm_object.py
jsonclasses/orm_query.py
jsonclasses/outils.py
jsonclasses/owned_collection_utils.py
jsonclasses/owned_dict.py
jsonclasses/owned_list.py
jsonclasses/pkgutils.py
jsonclasses/py.typed
jsonclasses/rtypes.py
jsonclasses/singleton.py
jsonclasses/types.py
jsonclasses/typing.py
jsonclasses/uconf.py
jsonclasses/uploaders.py
jsonclasses/user_conf.py
jsonclasses/vmsgcollector.py
jsonclasses/modifiers/__init__.py
jsonclasses/modifiers/abs_modifier.py
jsonclasses/modifiers/add_modifier.py
jsonclasses/modifiers/after_modifier.py
jsonclasses/modifiers/alnum_modifier.py
jsonclasses/modifiers/alpha_modifier.py
jsonclasses/modifiers/any_modifier.py
jsonclasses/modifiers/append_modifier.py
jsonclasses/modifiers/asop_modifier.py
jsonclasses/modifiers/asopd_modifier.py
jsonclasses/modifiers/assign_modifier.py
jsonclasses/modifiers/at_modifier.py
jsonclasses/modifiers/authby_modifier.py
jsonclasses/modifiers/authidentity_modifier.py
jsonclasses/modifiers/before_modifier.py
jsonclasses/modifiers/bool_modifier.py
jsonclasses/modifiers/canc_modifier.py
jsonclasses/modifiers/cancu_modifier.py
jsonclasses/modifiers/canr_modifier.py
jsonclasses/modifiers/canu_modifier.py
jsonclasses/modifiers/cascade_modifier.py
jsonclasses/modifiers/ceil_modifier.py
jsonclasses/modifiers/chained_modifier.py
jsonclasses-3.3.0.dist-info/LICENSE
jsonclasses-3.3.0.dist-info/METADATA
jsonclasses-3.3.0.dist-info/WHEEL
jsonclasses-3.3.0.dist-info/top_level.txt
jsonclasses-3.3.0.dist-info/RECORD
