Metadata-Version: 2.1
Name: jsonclasses
Version: 3.3.0
Summary: The modern declarative data flow pipeline and data graph framework for the AI empowered generation.
Home-page: https://github.com/fillmula/jsonclasses
Author: Fillmula Inc.
Author-email: victor.teo@fillmula.com
License: MIT
Platform: UNKNOWN
Classifier: Programming Language :: Python :: 3.10
Requires-Python: >=3.10
License-File: LICENSE
Requires-Dist: inflection-plus (==0.1.0)
Requires-Dist: bcrypt (<4.0.0,>=3.2.0)
